pyproject/__init__.py
pyproject/pyproject.py
pyproject_npp-0.2.dist-info/LICENSE
pyproject_npp-0.2.dist-info/METADATA
pyproject_npp-0.2.dist-info/WHEEL
pyproject_npp-0.2.dist-info/entry_points.txt
pyproject_npp-0.2.dist-info/top_level.txt
pyproject_npp-0.2.dist-info/RECORD
