Metadata-Version: 2.1
Name: pyproject-npp
Version: 0.2
Summary: Programa per tractament de fitxers.
Home-page: https://github.com/NilPujolPorta/pyproject
Author: Nil Pujol Porta
Author-email: nilpujolporta@gmail.com
License: GNU
Platform: UNKNOWN
License-File: LICENSE
Requires-Dist: argparse
Requires-Dist: setuptools (>=42)
Requires-Dist: wheel
Requires-Dist: Gooey
Requires-Dist: pytest-shutil
